graphql_subscription_manager/__init__.py
graphql_subscription_manager-0.7.1.dist-info/LICENSE
graphql_subscription_manager-0.7.1.dist-info/METADATA
graphql_subscription_manager-0.7.1.dist-info/WHEEL
graphql_subscription_manager-0.7.1.dist-info/top_level.txt
graphql_subscription_manager-0.7.1.dist-info/RECORD
