Metadata-Version: 2.1
Name: graphql-subscription-manager
Version: 0.7.1
Summary: A python3 library for graphql subscription manager
Home-page: https://github.com/Danielhiversen/PyGraphqlWebsocketManager
Author: Daniel Hjelseth Høyer
Author-email: mail@dahoiv.net
Classifier: Intended Audience :: Developers
Classifier: Operating System :: OS Independent
Classifier: Programming Language :: Python
Classifier: Programming Language :: Python :: 3
Classifier: Topic :: Home Automation
Classifier: Topic :: Software Development :: Libraries :: Python Modules
Requires-Python: >=3.9.0
License-File: LICENSE
Requires-Dist: websockets (>=8.0)
